promoe/__init__.py
promoe/cleanup.py
promoe/cli.py
promoe/promoe.py
promoe/pymol_scripts/__init__.py
promoe/pymol_scripts/altloc_extraction.py
promoe/pymol_scripts/extract_chains_only.py
promoe/pymol_scripts/extract_charges.py
promoe/pymol_scripts/extract_distances.py
promoe/pymol_scripts/extract_ligands.py
promoe/pymol_scripts/hydrogen_verification.py
promoe/svl_scripts/choose_atoms.svl
promoe/svl_scripts/convert_pdb_mol2.svl
promoe/svl_scripts/protonate.svl
promoe/svl_scripts/run_choose_atoms.sh
promoe/svl_scripts/run_pdb_convertion.sh
promoe/svl_scripts/run_protonate.sh
promoe/util/__init__.py
promoe/util/command_util.py
promoe/util/list_util.py
promoe-0.1.0.dist-info/AUTHORS.rst
promoe-0.1.0.dist-info/LICENSE
promoe-0.1.0.dist-info/METADATA
promoe-0.1.0.dist-info/WHEEL
promoe-0.1.0.dist-info/entry_points.txt
promoe-0.1.0.dist-info/top_level.txt
promoe-0.1.0.dist-info/RECORD
