Metadata-Version: 2.1
Name: promoe
Version: 0.1.0
Summary: Protonize a selection of atoms of protein binding sites.
Home-page: https://github.com/zethson/promoe
Author: Lukas Heumos
Author-email: lukas.heumos@posteo.net
License: GNU General Public License v3
Keywords: promoe
Platform: UNKNOWN
Classifier: Development Status :: 2 - Pre-Alpha
Classifier: Intended Audience :: Developers
Classifier: License :: OSI Approved :: GNU General Public License v3 (GPLv3)
Classifier: Natural Language :: English
Classifier: Programming Language :: Python :: 3
Classifier: Programming Language :: Python :: 3.6
Classifier: Programming Language :: Python :: 3.7
Requires-Python: !=3.0.*, !=3.1.*, !=3.2.*, !=3.3.*, !=3.4.*
Requires-Dist: click (==7.0)
Requires-Dist: pyyaml (==5.1.2)
Requires-Dist: tqdm (==4.36.1)
Requires-Dist: biopython (==1.74)
